commandsheet/__init__.py
commandsheet/__main__.py
commandsheet/cli.py
commandsheet/commandsheet.py
commandsheet/compatibility.py
commandsheet/config.py
commandsheet/const.py
commandsheet/errors.py
commandsheet/locale.py
commandsheet/output.py
commandsheet-0.2.0.dist-info/LICENSE
commandsheet-0.2.0.dist-info/METADATA
commandsheet-0.2.0.dist-info/WHEEL
commandsheet-0.2.0.dist-info/entry_points.txt
commandsheet-0.2.0.dist-info/top_level.txt
commandsheet-0.2.0.dist-info/RECORD
