Metadata-Version: 2.1
Name: commandsheet
Version: 0.2.0
Summary: Display catalog of commands user uses often.
Author: Niklas Larsson
Author-email: 
Project-URL: Source, https://github.com/nikkelarsson/commandsheet
Classifier: License :: OSI Approved :: MIT License
Requires-Python: >=3.7
License-File: LICENSE
Requires-Dist: attrs
Requires-Dist: rich
